trafficSimulator/__init__.py
trafficSimulator/core/simulation.py
trafficSimulator/core/vehicle.py
trafficSimulator/core/vehicle_generator.py
trafficSimulator/core/geometry/cubic_curve.py
trafficSimulator/core/geometry/quadratic_curve.py
trafficSimulator/core/geometry/segment.py
trafficSimulator/visualizer/window.py
trafficSimulator-0.0.1.dist-info/LICENSE
trafficSimulator-0.0.1.dist-info/METADATA
trafficSimulator-0.0.1.dist-info/WHEEL
trafficSimulator-0.0.1.dist-info/top_level.txt
trafficSimulator-0.0.1.dist-info/RECORD
